datalib/__init__.py
datalib/advanced_analysis.py
datalib/manipulation_data.py
datalib/statistics.py
datalib/visualization.py
datalibhope-1.0.0.dist-info/LICENSE
datalibhope-1.0.0.dist-info/METADATA
datalibhope-1.0.0.dist-info/WHEEL
datalibhope-1.0.0.dist-info/RECORD
